{
  "+919952164502": {
    "phone": "+919952164502",
    "name": "Keerthana",
    "email": "keerthanasri@gmail.com",
    "domain": "AI / ML",
    "goal": "placement",
    "target_companies": [],
    "assessed": false,
    "overall_readiness": null,
    "streak": 0,
    "days_inactive": null,
    "scores": {},
    "gaps": [],
    "applications": [],
    "weekly_stats": {
      "week_label": "19 Jun 2026",
      "hours_this_week": 0,
      "tasks_this_week": 0,
      "readiness_delta": null,
      "active_applications": 0,
      "offers": 0
    },
    "updated_at": "2026-06-18T20:16:32.941474+00:00"
  }
}